envit/__init__.py
envit/cli.py
envit/core.py
envit/encryption.py
envit-0.1.1.dist-info/LICENSE
envit-0.1.1.dist-info/METADATA
envit-0.1.1.dist-info/WHEEL
envit-0.1.1.dist-info/entry_points.txt
envit-0.1.1.dist-info/RECORD
