Metadata-Version: 2.1
Name: envit
Version: 0.1.1
Summary: Managing multiple environments credentials easily
License: MIT
Author: Hassan Saadat
Author-email: saadathassan34@gmail.com
Requires-Python: >=3.8,<4.0
Classifier: License :: OSI Approved :: MIT License
Classifier: Programming Language :: Python :: 3
Classifier: Programming Language :: Python :: 3.8
Classifier: Programming Language :: Python :: 3.9
Classifier: Programming Language :: Python :: 3.10
Classifier: Programming Language :: Python :: 3.11
Classifier: Programming Language :: Python :: 3.12
Requires-Dist: cryptography (>=42.0.5,<43.0.0)
Requires-Dist: python-decouple (>=3.8,<4.0)
